Metadata-Version: 1.0
Name: wireshark-ext
Version: 0.1
Summary: Wireshark Format Tool
Home-page: https://github.com/yafeile/wireshark_ext
Author: yafeile
Author-email: yafeile@sohu.com
License: UNKNOWN
Platform: UNKNOWN
